{
  "required_skills": [
    "KS122QL6NN356RRJT6RV",
    "KS127296VDYS7ZFWVC46",
    "ESAD92AA2437BEF8C136",
    "KS122QR6WQ8M7BLY05B3",
    "KS1289Y78X8HDRH2PLM8",
    "KS4415B77WWH2WCSVHCV",
    "KS122J76TK2KYM5FT2F3",
    "KS1222B6JMXHTMP5Z46Y",
    "ES92C25CB4A4612B2156",
    "KSS344MJ1FTC11D417OQ",
    "KS128D665S69115QGB5J",
    "KSDJCA4E89LB98JAZ7LZ",
    "ESE00213B4D58BD54EC1",
    "KS1208P6ZMZ4N872Y7X5",
    "KS127115XWT6H93XPX4X",
    "ES933D5DCC6C3A7C44D9",
    "ESC7869CF7378283E0AA",
    "KS440QS66YCBN23Y8K25",
    "KS121XY6VSGJ3Z6J82FQ",
    "KS120WT63K4HC6NX7QXV",
    "KS7R8G2D52QH187SED9R",
    "KS1217S6P3M284GY3DLN",
    "KS125TB6YR6236RKM563",
    "KSUS9XM8DSF96YI9S2QY",
    "KSP8M654PRZCT7JE9UU6",
    "KSY4WFI1S164RQUBSPCC",
    "KS124CH623PFBJS8T5KM",
    "KS120ST66K9HBSZ7MPS3",
    "KS123PN6QLC535X9L625",
    "KS125CS6L6H5LPLTZG0Q",
    "KSSGSFTDVI0J638VZ2RV",
    "KS128G66RG96FZNHFCXY",
    "KS125R96VYB8GM02DSMV",
    "KS7G6NF6D1PXYDWCK4GS",
    "KS4425C7820LCHZS7VGX",
    "KS1226N77K2R22TWDSSP",
    "KS7G0PK5YF5GV85CXJSX",
    "ESEB1D4619E6E83A061D",
    "KS121DV68XQ3HX9FLNCW",
    "KS4424T6KPTTQ1NKM0XK",
    "KS124RX787SQ1WVD8XF6",
    "KSZX7YZWNR5IDR1I2VMZ",
    "KS4401V5WX78L6JX0NW7",
    "ESA91D8112EB9ECA3570",
    "KSQY249T7UYPLS6LKBP0",
    "KS441LF7187KS0CV4B6Y",
    "KS441LG5Y8XGW9TP7B4W",
    "KS4400B70JFSWXTYH0P2",
    "KS126HV6CFLVGG8L97CP",
    "KS128BL6BPTLYCNXSGRS",
    "KSUDU9T83UZ7CK5THOYD",
    "KS441FR6L2YYQLPZBQRC",
    "KS1264M6STJ22H7GCK5N"
  ],
  "required_skills_after_noise_filter": [
    "KS122QL6NN356RRJT6RV",
    "KS127296VDYS7ZFWVC46",
    "ESAD92AA2437BEF8C136",
    "KS122QR6WQ8M7BLY05B3",
    "KS1289Y78X8HDRH2PLM8",
    "KS4415B77WWH2WCSVHCV",
    "KS122J76TK2KYM5FT2F3",
    "KS1222B6JMXHTMP5Z46Y",
    "ES92C25CB4A4612B2156",
    "KSS344MJ1FTC11D417OQ",
    "KS128D665S69115QGB5J",
    "KSDJCA4E89LB98JAZ7LZ",
    "ESE00213B4D58BD54EC1",
    "KS1208P6ZMZ4N872Y7X5",
    "KS127115XWT6H93XPX4X",
    "ES933D5DCC6C3A7C44D9",
    "ESC7869CF7378283E0AA",
    "KS121XY6VSGJ3Z6J82FQ",
    "KS120WT63K4HC6NX7QXV",
    "KS1217S6P3M284GY3DLN",
    "KS125TB6YR6236RKM563",
    "KSUS9XM8DSF96YI9S2QY",
    "KSP8M654PRZCT7JE9UU6",
    "KSY4WFI1S164RQUBSPCC",
    "KS124CH623PFBJS8T5KM",
    "KS120ST66K9HBSZ7MPS3",
    "KS123PN6QLC535X9L625",
    "KS125CS6L6H5LPLTZG0Q",
    "KSSGSFTDVI0J638VZ2RV",
    "KS128G66RG96FZNHFCXY",
    "KS7G6NF6D1PXYDWCK4GS",
    "KS1226N77K2R22TWDSSP",
    "KS7G0PK5YF5GV85CXJSX",
    "ESEB1D4619E6E83A061D",
    "KS121DV68XQ3HX9FLNCW",
    "KSZX7YZWNR5IDR1I2VMZ",
    "KS4401V5WX78L6JX0NW7",
    "ESA91D8112EB9ECA3570",
    "KSQY249T7UYPLS6LKBP0",
    "KS441LF7187KS0CV4B6Y",
    "KS441LG5Y8XGW9TP7B4W",
    "KS126HV6CFLVGG8L97CP",
    "KS128BL6BPTLYCNXSGRS",
    "KSUDU9T83UZ7CK5THOYD",
    "KS441FR6L2YYQLPZBQRC",
    "KS1264M6STJ22H7GCK5N"
  ],
  "skill_gap": [
    "KS122QL6NN356RRJT6RV",
    "KS127296VDYS7ZFWVC46",
    "ESAD92AA2437BEF8C136",
    "KS122QR6WQ8M7BLY05B3",
    "KS1289Y78X8HDRH2PLM8",
    "KS4415B77WWH2WCSVHCV",
    "KS122J76TK2KYM5FT2F3",
    "KS1222B6JMXHTMP5Z46Y",
    "ES92C25CB4A4612B2156",
    "KSS344MJ1FTC11D417OQ",
    "KS128D665S69115QGB5J",
    "KSDJCA4E89LB98JAZ7LZ",
    "ESE00213B4D58BD54EC1",
    "KS1208P6ZMZ4N872Y7X5",
    "KS127115XWT6H93XPX4X",
    "ES933D5DCC6C3A7C44D9",
    "ESC7869CF7378283E0AA",
    "KS121XY6VSGJ3Z6J82FQ",
    "KS120WT63K4HC6NX7QXV",
    "KS1217S6P3M284GY3DLN",
    "KS125TB6YR6236RKM563",
    "KSUS9XM8DSF96YI9S2QY",
    "KSP8M654PRZCT7JE9UU6",
    "KSY4WFI1S164RQUBSPCC",
    "KS124CH623PFBJS8T5KM",
    "KS120ST66K9HBSZ7MPS3",
    "KS123PN6QLC535X9L625",
    "KS125CS6L6H5LPLTZG0Q",
    "KSSGSFTDVI0J638VZ2RV",
    "KS128G66RG96FZNHFCXY",
    "KS7G6NF6D1PXYDWCK4GS",
    "KS1226N77K2R22TWDSSP",
    "KS7G0PK5YF5GV85CXJSX",
    "ESEB1D4619E6E83A061D",
    "KS121DV68XQ3HX9FLNCW",
    "KSZX7YZWNR5IDR1I2VMZ",
    "KSQY249T7UYPLS6LKBP0",
    "KS441LF7187KS0CV4B6Y",
    "KS441LG5Y8XGW9TP7B4W",
    "KS126HV6CFLVGG8L97CP",
    "KS128BL6BPTLYCNXSGRS",
    "KSUDU9T83UZ7CK5THOYD",
    "KS441FR6L2YYQLPZBQRC",
    "KS1264M6STJ22H7GCK5N"
  ],
  "counts": {
    "required_raw": 53,
    "required_filtered": 46,
    "gap": 44
  }
}